{"count":20,"next":null,"previous":null,"results":[{"creator":2215,"id":7624648,"image_id":null,"images":[{"architecture":"amd64","features":"","variant":null,"digest":"sha256:00fb9871cd9eaa80b7fd9f5e759555ed3459db7b251d2e5a9ee6802e1a0de2b3","os":"linux","os_features":"","os_version":null,"size":89961169,"status":"active","last_pulled":"2021-12-22T03:15:08.867161Z","last_pushed":"2021-09-29T10:50:25.291497Z"},{"architecture":"arm64","features":"","variant":"v8","digest":"sha256:9029930a6f6ead33140d771612c72a4911721ed04625655fbcb4b3a09ea66bb1","os":"linux","os_features":"","os_version":null,"size":87882018,"status":"active","last_pulled":"2021-12-22T03:15:09.627873Z","last_pushed":"2021-09-29T03:21:20.391418Z"}],"last_updated":"2021-09-29T10:50:36.181048Z","last_updater":1156886,"last_updater_username":"doijanky","name":"latest","repository":1195156,"full_size":89961169,"v2":true,"tag_status":"active","tag_last_pulled":"2021-12-22T03:15:09.627873Z","tag_last_pushed":"2021-09-29T10:50:36.181048Z"},{"creator":1156886,"id":17145894,"image_id":null,"images":[{"architecture":"amd64","features":"","variant":null,"digest":"sha256:00fb9871cd9eaa80b7fd9f5e759555ed3459db7b251d2e5a9ee6802e1a0de2b3","os":"linux","os_features":"","os_version":null,"size":89961169,"status":"active","last_pulled":"2021-12-22T03:15:08.867161Z","last_pushed":"2021-09-29T10:50:25.291497Z"},{"architecture":"arm64","features":"","variant":"v8","digest":"sha256:9029930a6f6ead33140d771612c72a4911721ed04625655fbcb4b3a09ea66bb1","os":"linux","os_features":"","os_version":null,"size":87882018,"status":"active","last_pulled":"2021-12-22T03:15:09.627873Z","last_pushed":"2021-09-29T03:21:20.391418Z"}],"last_updated":"2021-09-29T10:50:33.590635Z","last_updater":1156886,"last_updater_username":"doijanky","name":"5.4.6","repository":1195156,"full_size":89961169,"v2":true,"tag_status":"active","tag_last_pulled":"2021-12-22T03:15:09.627873Z","tag_last_pushed":"2021-09-29T10:50:33.590635Z"},{"creator":2215,"id":13696476,"image_id":null,"images":[{"architecture":"amd64","features":"","variant":null,"digest":"sha256:00fb9871cd9eaa80b7fd9f5e759555ed3459db7b251d2e5a9ee6802e1a0de2b3","os":"linux","os_features":"","os_version":null,"size":89961169,"status":"active","last_pulled":"2021-12-22T03:15:08.867161Z","last_pushed":"2021-09-29T10:50:25.291497Z"},{"architecture":"arm64","features":"","variant":"v8","digest":"sha256:9029930a6f6ead33140d771612c72a4911721ed04625655fbcb4b3a09ea66bb1","os":"linux","os_features":"","os_version":null,"size":87882018,"status":"active","last_pulled":"2021-12-22T03:15:09.627873Z","last_pushed":"2021-09-29T03:21:20.391418Z"}],"last_updated":"2021-09-29T10:50:30.651764Z","last_updater":1156886,"last_updater_username":"doijanky","name":"5.4","repository":1195156,"full_size":89961169,"v2":true,"tag_status":"active","tag_last_pulled":"2021-12-22T03:15:09.627873Z","tag_last_pushed":"2021-09-29T10:50:30.651764Z"},{"creator":2215,"id":7624644,"image_id":null,"images":[{"architecture":"amd64","features":"","variant":null,"digest":"sha256:00fb9871cd9eaa80b7fd9f5e759555ed3459db7b251d2e5a9ee6802e1a0de2b3","os":"linux","os_features":"","os_version":null,"size":89961169,"status":"active","last_pulled":"2021-12-22T03:15:08.867161Z","last_pushed":"2021-09-29T10:50:25.291497Z"},{"architecture":"arm64","features":"","variant":"v8","digest":"sha256:9029930a6f6ead33140d771612c72a4911721ed04625655fbcb4b3a09ea66bb1","os":"linux","os_features":"","os_version":null,"size":87882018,"status":"active","last_pulled":"2021-12-22T03:15:09.627873Z","last_pushed":"2021-09-29T03:21:20.391418Z"}],"last_updated":"2021-09-29T10:50:27.558335Z","last_updater":1156886,"last_updater_username":"doijanky","name":"5","repository":1195156,"full_size":89961169,"v2":true,"tag_status":"active","tag_last_pulled":"2021-12-22T03:15:09.627873Z","tag_last_pushed":"2021-09-29T10:50:27.558335Z"},{"creator":1156886,"id":16769273,"image_id":null,"images":[{"architecture":"amd64","features":"","variant":null,"digest":"sha256:205d8289dba42eb8cc2648656f530ffc41e67c56fb677e43dbf065e187d572ae","os":"linux","os_features":"","os_version":null,"size":95115523,"status":"inactive","last_pulled":null,"last_pushed":null}],"last_updated":"2017-10-18T22:42:54.552502Z","last_updater":1156886,"last_updater_username":"doijanky","name":"5.4.5","repository":1195156,"full_size":95115523,"v2":true,"tag_status":"inactive","tag_last_pulled":null,"tag_last_pushed":"2017-10-18T22:42:54.552502Z"},{"creator":2215,"id":14640965,"image_id":null,"images":[{"architecture":"amd64","features":"","variant":null,"digest":"sha256:ef57d51227e5dcf78ffa3caf6b8b96c68f0a7767e8027adab1e4c512bbfc5334","os":"linux","os_features":"","os_version":null,"size":310359653,"status":"inactive","last_pulled":null,"last_pushed":null}],"last_updated":"2017-10-12T18:42:59.713543Z","last_updater":1156886,"last_updater_username":"doijanky","name":"5.4.4","repository":1195156,"full_size":310359653,"v2":true,"tag_status":"inactive","tag_last_pulled":null,"tag_last_pushed":"2017-10-12T18:42:59.713543Z"},{"creator":2215,"id":14425276,"image_id":null,"images":[{"architecture":"amd64","features":"","variant":null,"digest":"sha256:77a766a67026855a043294eb75de26aff34ec0eed675705011b436ebe0614773","os":"linux","os_features":"","os_version":null,"size":309892791,"status":"inactive","last_pulled":null,"last_pushed":null}],"last_updated":"2017-08-26T04:25:18.148826Z","last_updater":2215,"last_updater_username":"stackbrew","name":"5.4.3","repository":1195156,"full_size":309892791,"v2":true,"tag_status":"inactive","tag_last_pulled":null,"tag_last_pushed":"2017-08-26T04:25:18.148826Z"},{"creator":2215,"id":14071580,"image_id":null,"images":[{"architecture":"amd64","features":"","variant":null,"digest":"sha256:2bcb2bc3c490072a26ffd855bb3e244eb7affe2f43dd62856070624f0976c9ff","os":"linux","os_features":"","os_version":null,"size":309890308,"status":"inactive","last_pulled":null,"last_pushed":null}],"last_updated":"2017-08-22T23:04:23.113692Z","last_updater":2215,"last_updater_username":"stackbrew","name":"5.4.2","repository":1195156,"full_size":309890308,"v2":true,"tag_status":"inactive","tag_last_pulled":null,"tag_last_pushed":"2017-08-22T23:04:23.113692Z"},{"creator":2215,"id":13807302,"image_id":null,"images":[{"architecture":"amd64","features":"","variant":null,"digest":"sha256:90970bf67ee882d8e738a15dd6f2672391959bb117b4d2425ab0cacbe0f41e9d","os":"linux","os_features":"","os_version":null,"size":310142261,"status":"inactive","last_pulled":null,"last_pushed":null}],"last_updated":"2017-08-08T21:45:16.496485Z","last_updater":2215,"last_updater_username":"stackbrew","name":"5.4.1","repository":1195156,"full_size":310142261,"v2":true,"tag_status":"inactive","tag_last_pulled":null,"tag_last_pushed":"2017-08-08T21:45:16.496485Z"},{"creator":2215,"id":13696470,"image_id":null,"images":[{"architecture":"amd64","features":"","variant":null,"digest":"sha256:002cf46ecf958e94d23f686e0646a5f12306d72d52e1c4cdf68478e20aea0f2b","os":"linux","os_features":"","os_version":null,"size":310141570,"status":"inactive","last_pulled":null,"last_pushed":null}],"last_updated":"2017-08-03T21:05:55.748184Z","last_updater":2215,"last_updater_username":"stackbrew","name":"5.4.0","repository":1195156,"full_size":310141570,"v2":true,"tag_status":"inactive","tag_last_pulled":null,"tag_last_pushed":"2017-08-03T21:05:55.748184Z"},{"creator":2215,"id":8531858,"image_id":null,"images":[{"architecture":"amd64","features":"","variant":null,"digest":"sha256:786b70f369334bf6aa134b37ae1946640bf2a1337bbe02515d2716ddbef558b2","os":"linux","os_features":"","os_version":null,"size":310182979,"status":"inactive","last_pulled":null,"last_pushed":null}],"last_updated":"2017-07-27T20:19:37.309406Z","last_updater":2215,"last_updater_username":"stackbrew","name":"5.3","repository":1195156,"full_size":310182979,"v2":true,"tag_status":"inactive","tag_last_pulled":null,"tag_last_pushed":"2017-07-27T20:19:37.309406Z"},{"creator":2215,"id":11656715,"image_id":null,"images":[{"architecture":"amd64","features":"","variant":null,"digest":"sha256:786b70f369334bf6aa134b37ae1946640bf2a1337bbe02515d2716ddbef558b2","os":"linux","os_features":"","os_version":null,"size":310182979,"status":"inactive","last_pulled":null,"last_pushed":null}],"last_updated":"2017-07-27T20:19:31.899053Z","last_updater":2215,"last_updater_username":"stackbrew","name":"5.3.5","repository":1195156,"full_size":310182979,"v2":true,"tag_status":"inactive","tag_last_pulled":null,"tag_last_pushed":"2017-07-27T20:19:31.899053Z"},{"creator":2215,"id":9635087,"image_id":null,"images":[{"architecture":"amd64","features":"","variant":null,"digest":"sha256:dddf5ee828f84830b24768f993cc5df94f90034448ca7510d791bd2bbbf618de","os":"linux","os_features":"","os_version":null,"size":252076892,"status":"inactive","last_pulled":null,"last_pushed":null}],"last_updated":"2017-05-22T19:02:27.596753Z","last_updater":2215,"last_updater_username":"stackbrew","name":"5.3.4","repository":1195156,"full_size":252076892,"v2":true,"tag_status":"inactive","tag_last_pulled":null,"tag_last_pushed":"2017-05-22T19:02:27.596753Z"},{"creator":2215,"id":9079340,"image_id":null,"images":[{"architecture":"amd64","features":"","variant":null,"digest":"sha256:764cc1dfcf95850dd47c36dcb80dc1cbce8f8ba4ab7d4bb910696cb3763b3a2a","os":"linux","os_features":"","os_version":null,"size":259539434,"status":"inactive","last_pulled":null,"last_pushed":null}],"last_updated":"2017-03-31T18:56:28.16327Z","last_updater":2215,"last_updater_username":"stackbrew","name":"5.3.3","repository":1195156,"full_size":259539434,"v2":true,"tag_status":"inactive","tag_last_pulled":null,"tag_last_pushed":"2017-03-31T18:56:28.16327Z"},{"creator":2215,"id":8728602,"image_id":null,"images":[{"architecture":"amd64","features":"","variant":null,"digest":"sha256:3956982f050f194f0d7cf51f632e7819530c3e640b9504cba0228da05025c36c","os":"linux","os_features":"","os_version":null,"size":259236221,"status":"inactive","last_pulled":null,"last_pushed":null}],"last_updated":"2017-03-07T19:45:59.48543Z","last_updater":2215,"last_updater_username":"stackbrew","name":"5.3.2","repository":1195156,"full_size":259236221,"v2":true,"tag_status":"inactive","tag_last_pulled":null,"tag_last_pushed":"2017-03-07T19:45:59.48543Z"},{"creator":2215,"id":8588634,"image_id":null,"images":[{"architecture":"amd64","features":"","variant":null,"digest":"sha256:8832c0453a23c59b082c92a67ba6fe70bc0e2af973901092d4cb4db688c1c694","os":"linux","os_features":"","os_version":null,"size":259232650,"status":"inactive","last_pulled":null,"last_pushed":null}],"last_updated":"2017-03-02T03:36:29.968482Z","last_updater":2215,"last_updater_username":"stackbrew","name":"5.3.1","repository":1195156,"full_size":259232650,"v2":true,"tag_status":"inactive","tag_last_pulled":null,"tag_last_pushed":"2017-03-02T03:36:29.968482Z"},{"creator":2215,"id":8531851,"image_id":null,"images":[{"architecture":"amd64","features":"","variant":null,"digest":"sha256:186efa1f967dd34375e8c896d558e3640a6c4179c45000fad8200e496e515d08","os":"linux","os_features":"","os_version":null,"size":258968924,"status":"inactive","last_pulled":null,"last_pushed":null}],"last_updated":"2017-02-28T00:44:11.636377Z","last_updater":2215,"last_updater_username":"stackbrew","name":"5.3.0","repository":1195156,"full_size":258968924,"v2":true,"tag_status":"inactive","tag_last_pulled":null,"tag_last_pushed":"2017-02-28T00:44:11.636377Z"},{"creator":2215,"id":7624632,"image_id":null,"images":[{"architecture":"amd64","features":"","variant":null,"digest":"sha256:f4f0feaa3d4f04788358f0e9762cf8443b17e79611c70f4d855fbe4040fe3025","os":"linux","os_features":"","os_version":null,"size":133737115,"status":"inactive","last_pulled":null,"last_pushed":null}],"last_updated":"2017-01-24T17:30:35.24779Z","last_updater":2215,"last_updater_username":"stackbrew","name":"5.2","repository":1195156,"full_size":133737115,"v2":true,"tag_status":"inactive","tag_last_pulled":null,"tag_last_pushed":"2017-01-24T17:30:35.24779Z"},{"creator":2215,"id":7647876,"image_id":null,"images":[{"architecture":"amd64","features":"","variant":null,"digest":"sha256:f4f0feaa3d4f04788358f0e9762cf8443b17e79611c70f4d855fbe4040fe3025","os":"linux","os_features":"","os_version":null,"size":133737115,"status":"inactive","last_pulled":null,"last_pushed":null}],"last_updated":"2017-01-24T17:30:21.091196Z","last_updater":2215,"last_updater_username":"stackbrew","name":"5.2.8","repository":1195156,"full_size":133737115,"v2":true,"tag_status":"inactive","tag_last_pulled":null,"tag_last_pushed":"2017-01-24T17:30:21.091196Z"},{"creator":2215,"id":7624608,"image_id":null,"images":[{"architecture":"amd64","features":"","variant":null,"digest":"sha256:787a5746fb92c2f4bef0bbb6341a2fc2fff9651a429b90dbfa03d5eae94d9211","os":"linux","os_features":"","os_version":null,"size":133734771,"status":"inactive","last_pulled":null,"last_pushed":null}],"last_updated":"2017-01-23T22:56:00.522291Z","last_updater":2215,"last_updater_username":"stackbrew","name":"5.2.6","repository":1195156,"full_size":133734771,"v2":true,"tag_status":"inactive","tag_last_pulled":null,"tag_last_pushed":"2017-01-23T22:56:00.522291Z"}]}
