{"count":32,"next":null,"previous":null,"results":[{"creator":2215,"id":8564837,"image_id":null,"images":[{"architecture":"arm64","features":"","variant":"v8","digest":"sha256:32a15a53851d57b0b0d6d968e70e9e9b4055786c7af4bb29a68812b7d8f1bc33","os":"linux","os_features":"","os_version":null,"size":129850503,"status":"active","last_pulled":"2021-12-22T09:56:51.1007Z","last_pushed":"2021-11-13T11:42:59.659031Z"},{"architecture":"amd64","features":"","variant":null,"digest":"sha256:d329c4065eaf249484dcb710b0ceb82231295abe805bad1eb9e4ba63195c4fa9","os":"linux","os_features":"","os_version":null,"size":138552631,"status":"active","last_pulled":"2021-12-22T11:02:49.1448Z","last_pushed":"2021-11-13T11:42:58.395578Z"},{"architecture":"arm","features":"","variant":"v6","digest":"sha256:26f8843b164895a859ea39130cbdb5f74395745e7b4fb9c712e0b19976b604fa","os":"linux","os_features":"","os_version":null,"size":122189311,"status":"active","last_pulled":"2021-12-22T09:56:50.371463Z","last_pushed":"2021-11-12T18:02:38.248737Z"}],"last_updated":"2021-11-13T11:43:21.209077Z","last_updater":1156886,"last_updater_username":"doijanky","name":"latest","repository":1288811,"full_size":138552631,"v2":true,"tag_status":"active","tag_last_pulled":"2021-12-22T11:02:49.1448Z","tag_last_pushed":"2021-11-13T11:43:21.209077Z"},{"creator":2215,"id":8564882,"image_id":null,"images":[{"architecture":"amd64","features":"","variant":null,"digest":"sha256:451c8ff71f6bc412949398c5339bffbbed66bcecaae2ec8bf13d839a66a0ae6a","os":"linux","os_features":"","os_version":null,"size":46198952,"status":"active","last_pulled":"2021-12-22T10:59:02.452061Z","last_pushed":"2021-11-13T11:43:08.228043Z"},{"architecture":"arm64","features":"","variant":"v8","digest":"sha256:a3e3dc0a58f72d85236d6a372a3d59c1bc8c89605019732e00419c9ee0ab1870","os":"linux","os_features":"","os_version":null,"size":45954234,"status":"active","last_pulled":"2021-12-22T09:25:49.875019Z","last_pushed":"2021-11-13T11:43:09.430829Z"},{"architecture":"arm","features":"","variant":"v6","digest":"sha256:368ce5d9175f8d71dc16dc4804766e6e6c6bbe2f833e91d25b392fe665f3b56e","os":"linux","os_features":"","os_version":null,"size":44286892,"status":"active","last_pulled":"2021-12-22T09:56:52.816837Z","last_pushed":"2021-11-12T18:02:46.065648Z"}],"last_updated":"2021-11-13T11:43:23.994546Z","last_updater":1156886,"last_updater_username":"doijanky","name":"slim","repository":1288811,"full_size":46198952,"v2":true,"tag_status":"active","tag_last_pulled":"2021-12-22T10:59:02.452061Z","tag_last_pushed":"2021-11-13T11:43:23.994546Z"},{"creator":1156886,"id":116532290,"image_id":null,"images":[{"architecture":"arm64","features":"","variant":"v8","digest":"sha256:a3e3dc0a58f72d85236d6a372a3d59c1bc8c89605019732e00419c9ee0ab1870","os":"linux","os_features":"","os_version":null,"size":45954234,"status":"active","last_pulled":"2021-12-22T09:25:49.875019Z","last_pushed":"2021-11-13T11:43:09.430829Z"},{"architecture":"amd64","features":"","variant":null,"digest":"sha256:451c8ff71f6bc412949398c5339bffbbed66bcecaae2ec8bf13d839a66a0ae6a","os":"linux","os_features":"","os_version":null,"size":46198952,"status":"active","last_pulled":"2021-12-22T10:59:02.452061Z","last_pushed":"2021-11-13T11:43:08.228043Z"},{"architecture":"arm","features":"","variant":"v6","digest":"sha256:368ce5d9175f8d71dc16dc4804766e6e6c6bbe2f833e91d25b392fe665f3b56e","os":"linux","os_features":"","os_version":null,"size":44286892,"status":"active","last_pulled":"2021-12-22T09:56:52.816837Z","last_pushed":"2021-11-12T18:02:46.065648Z"}],"last_updated":"2021-11-13T11:43:18.566013Z","last_updater":1156886,"last_updater_username":"doijanky","name":"1.8.2-slim","repository":1288811,"full_size":46198952,"v2":true,"tag_status":"active","tag_last_pulled":"2021-12-22T10:59:02.452061Z","tag_last_pushed":"2021-11-13T11:43:18.566013Z"},{"creator":1156886,"id":116532285,"image_id":null,"images":[{"architecture":"amd64","features":"","variant":null,"digest":"sha256:d329c4065eaf249484dcb710b0ceb82231295abe805bad1eb9e4ba63195c4fa9","os":"linux","os_features":"","os_version":null,"size":138552631,"status":"active","last_pulled":"2021-12-22T11:02:49.1448Z","last_pushed":"2021-11-13T11:42:58.395578Z"},{"architecture":"arm64","features":"","variant":"v8","digest":"sha256:32a15a53851d57b0b0d6d968e70e9e9b4055786c7af4bb29a68812b7d8f1bc33","os":"linux","os_features":"","os_version":null,"size":129850503,"status":"active","last_pulled":"2021-12-22T09:56:51.1007Z","last_pushed":"2021-11-13T11:42:59.659031Z"},{"architecture":"arm","features":"","variant":"v6","digest":"sha256:26f8843b164895a859ea39130cbdb5f74395745e7b4fb9c712e0b19976b604fa","os":"linux","os_features":"","os_version":null,"size":122189311,"status":"active","last_pulled":"2021-12-22T09:56:50.371463Z","last_pushed":"2021-11-12T18:02:38.248737Z"}],"last_updated":"2021-11-13T11:43:14.823742Z","last_updater":1156886,"last_updater_username":"doijanky","name":"1.8.2","repository":1288811,"full_size":138552631,"v2":true,"tag_status":"active","tag_last_pulled":"2021-12-22T11:02:49.1448Z","tag_last_pushed":"2021-11-13T11:43:14.823742Z"},{"creator":1156886,"id":98467604,"image_id":null,"images":[{"architecture":"arm","features":"","variant":"v6","digest":"sha256:368ce5d9175f8d71dc16dc4804766e6e6c6bbe2f833e91d25b392fe665f3b56e","os":"linux","os_features":"","os_version":null,"size":44286892,"status":"active","last_pulled":"2021-12-22T09:56:52.816837Z","last_pushed":"2021-11-12T18:02:46.065648Z"},{"architecture":"arm64","features":"","variant":"v8","digest":"sha256:a3e3dc0a58f72d85236d6a372a3d59c1bc8c89605019732e00419c9ee0ab1870","os":"linux","os_features":"","os_version":null,"size":45954234,"status":"active","last_pulled":"2021-12-22T09:25:49.875019Z","last_pushed":"2021-11-13T11:43:09.430829Z"},{"architecture":"amd64","features":"","variant":null,"digest":"sha256:451c8ff71f6bc412949398c5339bffbbed66bcecaae2ec8bf13d839a66a0ae6a","os":"linux","os_features":"","os_version":null,"size":46198952,"status":"active","last_pulled":"2021-12-22T10:59:02.452061Z","last_pushed":"2021-11-13T11:43:08.228043Z"}],"last_updated":"2021-11-13T11:43:11.736799Z","last_updater":1156886,"last_updater_username":"doijanky","name":"1.8-slim","repository":1288811,"full_size":46198952,"v2":true,"tag_status":"active","tag_last_pulled":"2021-12-22T10:59:02.452061Z","tag_last_pushed":"2021-11-13T11:43:11.736799Z"},{"creator":1156886,"id":98467590,"image_id":null,"images":[{"architecture":"amd64","features":"","variant":null,"digest":"sha256:d329c4065eaf249484dcb710b0ceb82231295abe805bad1eb9e4ba63195c4fa9","os":"linux","os_features":"","os_version":null,"size":138552631,"status":"active","last_pulled":"2021-12-22T11:02:49.1448Z","last_pushed":"2021-11-13T11:42:58.395578Z"},{"architecture":"arm64","features":"","variant":"v8","digest":"sha256:32a15a53851d57b0b0d6d968e70e9e9b4055786c7af4bb29a68812b7d8f1bc33","os":"linux","os_features":"","os_version":null,"size":129850503,"status":"active","last_pulled":"2021-12-22T09:56:51.1007Z","last_pushed":"2021-11-13T11:42:59.659031Z"},{"architecture":"arm","features":"","variant":"v6","digest":"sha256:26f8843b164895a859ea39130cbdb5f74395745e7b4fb9c712e0b19976b604fa","os":"linux","os_features":"","os_version":null,"size":122189311,"status":"active","last_pulled":"2021-12-22T09:56:50.371463Z","last_pushed":"2021-11-12T18:02:38.248737Z"}],"last_updated":"2021-11-13T11:43:01.893861Z","last_updater":1156886,"last_updater_username":"doijanky","name":"1.8","repository":1288811,"full_size":138552631,"v2":true,"tag_status":"active","tag_last_pulled":"2021-12-22T11:02:49.1448Z","tag_last_pushed":"2021-11-13T11:43:01.893861Z"},{"creator":1156886,"id":98467620,"image_id":null,"images":[{"architecture":"arm","features":"","variant":"v6","digest":"sha256:bad920760d8d3c4f958c916e02150fd4a4c180022e3ff906d298e61a7a701e91","os":"linux","os_features":"","os_version":null,"size":58246607,"status":"active","last_pulled":"2021-12-22T09:56:51.143381Z","last_pushed":null},{"architecture":"amd64","features":"","variant":null,"digest":"sha256:71f6b3fa0531162741ae8349ff6707c7ab6bb5289a5416ae4cc7ca69ca6b63f0","os":"linux","os_features":"","os_version":null,"size":60217306,"status":"active","last_pulled":"2021-12-22T09:56:50.276974Z","last_pushed":null},{"architecture":"arm64","features":"","variant":"v8","digest":"sha256:7d4a43ee00e9ee24bbb742b8ae55b86a2f1f4d106cf56252e45e04f6d9f68f3d","os":"linux","os_features":"","os_version":null,"size":60037196,"status":"active","last_pulled":"2021-12-22T09:56:51.919274Z","last_pushed":null}],"last_updated":"2020-06-22T20:29:07.710467Z","last_updater":1156886,"last_updater_username":"doijanky","name":"1.8.0-slim","repository":1288811,"full_size":0,"v2":true,"tag_status":"active","tag_last_pulled":"2021-12-22T09:56:51.919274Z","tag_last_pushed":"2020-06-22T20:29:07.710467Z"},{"creator":1156886,"id":98467611,"image_id":null,"images":[{"architecture":"arm64","features":"","variant":"v8","digest":"sha256:81d0da9a7c9da40f36d808c262ff710b29540e64e26f0bab948358a339606d89","os":"linux","os_features":"","os_version":null,"size":135290115,"status":"active","last_pulled":"2021-12-22T09:56:59.509692Z","last_pushed":null},{"architecture":"arm","features":"","variant":"v6","digest":"sha256:ebf5be574d491f348d9374455a0d40e9b9e9c072d389439f032fd520ec37c03e","os":"linux","os_features":"","os_version":null,"size":129679097,"status":"active","last_pulled":"2021-12-22T09:56:58.718598Z","last_pushed":null},{"architecture":"amd64","features":"","variant":null,"digest":"sha256:57cb594bd7577d8482d20b3c5d1999de70020ed953b4e84e9fde0574d1c804e7","os":"linux","os_features":"","os_version":null,"size":145471759,"status":"active","last_pulled":"2021-12-22T09:56:57.929203Z","last_pushed":null}],"last_updated":"2020-06-22T20:28:50.178905Z","last_updater":1156886,"last_updater_username":"doijanky","name":"1.8.0","repository":1288811,"full_size":0,"v2":true,"tag_status":"active","tag_last_pulled":"2021-12-22T09:56:59.509692Z","tag_last_pushed":"2020-06-22T20:28:50.178905Z"},{"creator":1156886,"id":105838247,"image_id":null,"images":[{"architecture":"arm64","features":"","variant":"v8","digest":"sha256:45db8a930c474ec1b471d330f0d7837817781f442781660d54b83c957d3913d0","os":"linux","os_features":"","os_version":null,"size":60038258,"status":"active","last_pulled":"2021-12-22T09:56:51.205967Z","last_pushed":null},{"architecture":"arm","features":"","variant":"v6","digest":"sha256:d3c7b98cfcba827ef928f67d651ae54d93f37e5ec1f4aa8da129a605ea887138","os":"linux","os_features":"","os_version":null,"size":58223280,"status":"active","last_pulled":"2021-12-22T09:56:50.474578Z","last_pushed":null},{"architecture":"amd64","features":"","variant":null,"digest":"sha256:befd9ba6f2781b5a6afcc0360dbc8ddaee995cbafa48e642b85e111f235425c4","os":"linux","os_features":"","os_version":null,"size":60217659,"status":"active","last_pulled":"2021-12-22T09:56:49.732547Z","last_pushed":null}],"last_updated":"2020-06-22T18:35:18.559302Z","last_updater":1156886,"last_updater_username":"doijanky","name":"1.8.1-slim","repository":1288811,"full_size":0,"v2":true,"tag_status":"active","tag_last_pulled":"2021-12-22T09:56:51.205967Z","tag_last_pushed":"2020-06-22T18:35:18.559302Z"},{"creator":1156886,"id":105838233,"image_id":null,"images":[{"architecture":"amd64","features":"","variant":null,"digest":"sha256:f05fa99cf91c247467afad3c0ad3fd262a6f8f27fccc36a8446837db52f3e6c0","os":"linux","os_features":"","os_version":null,"size":145467376,"status":"active","last_pulled":"2021-12-22T09:56:59.295913Z","last_pushed":null},{"architecture":"arm","features":"","variant":"v6","digest":"sha256:b26ae39f9e9f766b5a8409c6b6d134768efcbb3af5f0ab213ba6e77b5c57e919","os":"linux","os_features":"","os_version":null,"size":129651275,"status":"active","last_pulled":"2021-12-22T09:57:00.033939Z","last_pushed":null},{"architecture":"arm64","features":"","variant":"v8","digest":"sha256:9b1369022519d39413ce456ee0368eaa3a8b6720ba32d9beee434c0bb8ac5c4e","os":"linux","os_features":"","os_version":null,"size":135289590,"status":"active","last_pulled":"2021-12-22T09:57:00.757843Z","last_pushed":null}],"last_updated":"2020-06-22T18:35:14.687212Z","last_updater":1156886,"last_updater_username":"doijanky","name":"1.8.1","repository":1288811,"full_size":0,"v2":true,"tag_status":"active","tag_last_pulled":"2021-12-22T09:57:00.757843Z","tag_last_pushed":"2020-06-22T18:35:14.687212Z"},{"creator":1156886,"id":70479792,"image_id":null,"images":[{"architecture":"arm64","features":"","variant":"v8","digest":"sha256:e1baa681223a3a4525878b1759f5989cc7c3fa158878cbf962ea87f7f7b05a0c","os":"linux","os_features":"","os_version":null,"size":59431622,"status":"active","last_pulled":"2021-12-22T09:56:55.441136Z","last_pushed":null},{"architecture":"arm","features":"","variant":"v6","digest":"sha256:b7d09fa9d23bfac547c76ca4a45fa544ad6635151da789b06219be4eeabc2938","os":"linux","os_features":"","os_version":null,"size":57082081,"status":"active","last_pulled":"2021-12-22T09:56:54.707407Z","last_pushed":null},{"architecture":"amd64","features":"","variant":null,"digest":"sha256:274127c4173d07be36323b165435516afbfb9d3fee5d0d5666274aa34bace58e","os":"linux","os_features":"","os_version":null,"size":59519389,"status":"active","last_pulled":"2021-12-22T09:56:53.911705Z","last_pushed":null}],"last_updated":"2020-04-24T15:35:51.396737Z","last_updater":1156886,"last_updater_username":"doijanky","name":"1.7.5-slim","repository":1288811,"full_size":59519389,"v2":true,"tag_status":"active","tag_last_pulled":"2021-12-22T09:56:55.441136Z","tag_last_pushed":"2020-04-24T15:35:51.396737Z"},{"creator":1156886,"id":70479782,"image_id":null,"images":[{"architecture":"amd64","features":"","variant":null,"digest":"sha256:33a0d224e9cfe670b31f2c984a9f1fd019cb5086073e99e0b1d4fdddf32cfb84","os":"linux","os_features":"","os_version":null,"size":140548151,"status":"active","last_pulled":"2021-12-22T09:56:56.517909Z","last_pushed":null},{"architecture":"arm64","features":"","variant":"v8","digest":"sha256:5c80a894f404aef89f5e1ac22d001285e3b767d893cca887a63e5b1b72a5247b","os":"linux","os_features":"","os_version":null,"size":132607770,"status":"active","last_pulled":"2021-12-22T09:56:57.953542Z","last_pushed":null},{"architecture":"arm","features":"","variant":"v6","digest":"sha256:10478eb842ef1f650befc3ec32be7046f2c7906565166d3d24181c88c1e196a5","os":"linux","os_features":"","os_version":null,"size":126346994,"status":"active","last_pulled":"2021-12-22T09:56:57.222358Z","last_pushed":null}],"last_updated":"2020-04-24T15:35:45.371843Z","last_updater":1156886,"last_updater_username":"doijanky","name":"1.7.5","repository":1288811,"full_size":140548151,"v2":true,"tag_status":"active","tag_last_pulled":"2021-12-22T09:56:57.953542Z","tag_last_pushed":"2020-04-24T15:35:45.371843Z"},{"creator":1156886,"id":26792721,"image_id":null,"images":[{"architecture":"amd64","features":"","variant":null,"digest":"sha256:274127c4173d07be36323b165435516afbfb9d3fee5d0d5666274aa34bace58e","os":"linux","os_features":"","os_version":null,"size":59519389,"status":"active","last_pulled":"2021-12-22T09:56:53.911705Z","last_pushed":null},{"architecture":"arm","features":"","variant":"v6","digest":"sha256:b7d09fa9d23bfac547c76ca4a45fa544ad6635151da789b06219be4eeabc2938","os":"linux","os_features":"","os_version":null,"size":57082081,"status":"active","last_pulled":"2021-12-22T09:56:54.707407Z","last_pushed":null},{"architecture":"arm64","features":"","variant":"v8","digest":"sha256:e1baa681223a3a4525878b1759f5989cc7c3fa158878cbf962ea87f7f7b05a0c","os":"linux","os_features":"","os_version":null,"size":59431622,"status":"active","last_pulled":"2021-12-22T09:56:55.441136Z","last_pushed":null}],"last_updated":"2020-04-24T15:35:42.316985Z","last_updater":1156886,"last_updater_username":"doijanky","name":"1.7-slim","repository":1288811,"full_size":59519389,"v2":true,"tag_status":"active","tag_last_pulled":"2021-12-22T09:56:55.441136Z","tag_last_pushed":"2020-04-24T15:35:42.316985Z"},{"creator":1156886,"id":26795530,"image_id":null,"images":[{"architecture":"arm64","features":"","variant":"v8","digest":"sha256:5c80a894f404aef89f5e1ac22d001285e3b767d893cca887a63e5b1b72a5247b","os":"linux","os_features":"","os_version":null,"size":132607770,"status":"active","last_pulled":"2021-12-22T09:56:57.953542Z","last_pushed":null},{"architecture":"amd64","features":"","variant":null,"digest":"sha256:33a0d224e9cfe670b31f2c984a9f1fd019cb5086073e99e0b1d4fdddf32cfb84","os":"linux","os_features":"","os_version":null,"size":140548151,"status":"active","last_pulled":"2021-12-22T09:56:56.517909Z","last_pushed":null},{"architecture":"arm","features":"","variant":"v6","digest":"sha256:10478eb842ef1f650befc3ec32be7046f2c7906565166d3d24181c88c1e196a5","os":"linux","os_features":"","os_version":null,"size":126346994,"status":"active","last_pulled":"2021-12-22T09:56:57.222358Z","last_pushed":null}],"last_updated":"2020-04-24T15:35:31.794957Z","last_updater":1156886,"last_updater_username":"doijanky","name":"1.7","repository":1288811,"full_size":140548151,"v2":true,"tag_status":"active","tag_last_pulled":"2021-12-22T09:56:57.953542Z","tag_last_pushed":"2020-04-24T15:35:31.794957Z"},{"creator":1156886,"id":59977145,"image_id":null,"images":[{"architecture":"amd64","features":"","variant":null,"digest":"sha256:583f564b35d4cd2e19b978f7252af30c499d43e97960100c9f2a61473f7ad6c8","os":"linux","os_features":"","os_version":null,"size":30891589,"status":"active","last_pulled":"2021-12-22T09:56:59.300709Z","last_pushed":null},{"architecture":"arm","features":"","variant":"v6","digest":"sha256:bc7fc10c9b04539d46a659599ea8f983873e42d52f941850b87fae692de71047","os":"linux","os_features":"","os_version":null,"size":29536474,"status":"active","last_pulled":"2021-12-22T09:57:00.056936Z","last_pushed":null},{"architecture":"arm64","features":"","variant":"v8","digest":"sha256:b51436ec47b71ed7f8bb57d5b061b03076bf67c241c2236ed573092c66d6b534","os":"linux","os_features":"","os_version":null,"size":30158334,"status":"active","last_pulled":"2021-12-22T09:57:00.741381Z","last_pushed":null}],"last_updated":"2019-06-25T01:51:18.199377Z","last_updater":1156886,"last_updater_username":"doijanky","name":"1.7.4-slim","repository":1288811,"full_size":30891589,"v2":true,"tag_status":"active","tag_last_pulled":"2021-12-22T09:57:00.741381Z","tag_last_pushed":"2019-06-25T01:51:18.199377Z"},{"creator":1156886,"id":59977144,"image_id":null,"images":[{"architecture":"amd64","features":"","variant":null,"digest":"sha256:45da44d338c0fd64c5c638cdcd5043ec384c774bc2a197de97f5cef067b4ac8f","os":"linux","os_features":"","os_version":null,"size":122596630,"status":"active","last_pulled":"2021-12-22T09:56:56.586182Z","last_pushed":null},{"architecture":"arm64","features":"","variant":"v8","digest":"sha256:829ca6c8d8804a20369e9641d721e52d3b1f062621770aa314cee3cea76b361d","os":"linux","os_features":"","os_version":null,"size":112904665,"status":"active","last_pulled":"2021-12-22T09:56:58.091459Z","last_pushed":null},{"architecture":"arm","features":"","variant":"v6","digest":"sha256:377f050bf927b21cc6e60fc904b568326e9afa8cdf0a7334d81f758932e4d0d5","os":"linux","os_features":"","os_version":null,"size":109878057,"status":"active","last_pulled":"2021-12-22T09:56:57.370519Z","last_pushed":null}],"last_updated":"2019-06-25T01:51:14.001336Z","last_updater":1156886,"last_updater_username":"doijanky","name":"1.7.4","repository":1288811,"full_size":122596630,"v2":true,"tag_status":"active","tag_last_pulled":"2021-12-22T09:56:58.091459Z","tag_last_pushed":"2019-06-25T01:51:14.001336Z"},{"creator":1156886,"id":51542990,"image_id":null,"images":[{"architecture":"arm64","features":"","variant":"v8","digest":"sha256:4ffeae3ef204b6e19254896dcbdbba74e5789d1a6df55c554a747073e80c43bc","os":"linux","os_features":"","os_version":null,"size":30158106,"status":"active","last_pulled":"2021-12-22T09:56:55.074027Z","last_pushed":null},{"architecture":"amd64","features":"","variant":null,"digest":"sha256:f2220076d6ec022f74d97ff4e26922bf841356336178cc4a4ffb2d0fb63b2094","os":"linux","os_features":"","os_version":null,"size":30887328,"status":"active","last_pulled":"2021-12-22T09:56:53.494223Z","last_pushed":null},{"architecture":"arm","features":"","variant":"v6","digest":"sha256:caada67ef2c0972c771536c3241c9ca05d36d29c38660c42a819b330080364f5","os":"linux","os_features":"","os_version":null,"size":29541311,"status":"active","last_pulled":"2021-12-22T09:56:54.273525Z","last_pushed":null}],"last_updated":"2019-06-19T23:50:50.909661Z","last_updater":1156886,"last_updater_username":"doijanky","name":"1.7.3-slim","repository":1288811,"full_size":30887328,"v2":true,"tag_status":"active","tag_last_pulled":"2021-12-22T09:56:55.074027Z","tag_last_pushed":"2019-06-19T23:50:50.909661Z"},{"creator":1156886,"id":51542973,"image_id":null,"images":[{"architecture":"amd64","features":"","variant":null,"digest":"sha256:d44011ca3e3202546047f10532efd5e218e53cc9063f909c76aef6989a82fcd4","os":"linux","os_features":"","os_version":null,"size":122556362,"status":"active","last_pulled":"2021-12-22T09:56:54.548096Z","last_pushed":null},{"architecture":"arm64","features":"","variant":"v8","digest":"sha256:899c7c27e85301c4c8bfb61526b26755c20fbf86aabdd7da3fcd79d98d1392e1","os":"linux","os_features":"","os_version":null,"size":112904799,"status":"active","last_pulled":"2021-12-22T09:56:56.059796Z","last_pushed":null},{"architecture":"arm","features":"","variant":"v6","digest":"sha256:da81d9a1334082707a157104e642ab41e968c1452a77f2b2a6e5d8330dfb014d","os":"linux","os_features":"","os_version":null,"size":109865585,"status":"active","last_pulled":"2021-12-22T09:56:55.318574Z","last_pushed":null}],"last_updated":"2019-06-19T23:50:49.114205Z","last_updater":1156886,"last_updater_username":"doijanky","name":"1.7.3","repository":1288811,"full_size":122556362,"v2":true,"tag_status":"active","tag_last_pulled":"2021-12-22T09:56:56.059796Z","tag_last_pushed":"2019-06-19T23:50:49.114205Z"},{"creator":1156886,"id":45466706,"image_id":null,"images":[{"architecture":"amd64","features":"","variant":null,"digest":"sha256:027814c51aef8e1e9442118dae216c6a991f7d3d57c544cee852cda02bdf21df","os":"linux","os_features":"","os_version":null,"size":30884931,"status":"inactive","last_pulled":null,"last_pushed":null},{"architecture":"arm","features":"","variant":"v6","digest":"sha256:5b619779bbe4ba4424e8deb16a33d0e239d89a26f04447e434b95a6b48b911ed","os":"linux","os_features":"","os_version":null,"size":29531693,"status":"inactive","last_pulled":null,"last_pushed":null},{"architecture":"arm64","features":"","variant":"v8","os":"linux","os_features":"","os_version":null,"size":30159287,"status":"inactive","last_pulled":null,"last_pushed":null}],"last_updated":"2019-03-08T19:00:57.827053Z","last_updater":1156886,"last_updater_username":"doijanky","name":"1.7.2-slim","repository":1288811,"full_size":30884931,"v2":true,"tag_status":"inactive","tag_last_pulled":null,"tag_last_pushed":"2019-03-08T19:00:57.827053Z"},{"creator":1156886,"id":45466676,"image_id":null,"images":[{"architecture":"amd64","features":"","variant":null,"digest":"sha256:bc0f646c1ede56bfb290e8f50281b7c417acc0ed3e023122206f7a95469851ff","os":"linux","os_features":"","os_version":null,"size":122549693,"status":"inactive","last_pulled":null,"last_pushed":null},{"architecture":"arm","features":"","variant":"v6","digest":"sha256:1282265b381289034a5bb5ba37a495cb990e733906e57c3e4806768f52c3a513","os":"linux","os_features":"","os_version":null,"size":109854024,"status":"inactive","last_pulled":null,"last_pushed":null},{"architecture":"arm64","features":"","variant":"v8","digest":"sha256:7442acbac71cfdef58abd77572b16960e6fa063bef2261f552cf941c1399aeb2","os":"linux","os_features":"","os_version":null,"size":112877048,"status":"inactive","last_pulled":null,"last_pushed":null}],"last_updated":"2019-03-08T19:00:30.757763Z","last_updater":1156886,"last_updater_username":"doijanky","name":"1.7.2","repository":1288811,"full_size":122549693,"v2":true,"tag_status":"inactive","tag_last_pulled":null,"tag_last_pushed":"2019-03-08T19:00:30.757763Z"},{"creator":1156886,"id":31409549,"image_id":null,"images":[{"architecture":"amd64","features":"","variant":null,"digest":"sha256:304f8cd4bc0c5e50d5a29bc5e7b5ee4adfd664ee62b6a73ff39e046e058a99da","os":"linux","os_features":"","os_version":null,"size":122491901,"status":"inactive","last_pulled":null,"last_pushed":null},{"architecture":"arm","features":"","variant":"v6","digest":"sha256:2128a99fb1e954d87a7af5c9909d4abbc1a774a33ecd71ce969b25389f58de00","os":"linux","os_features":"","os_version":null,"size":109803150,"status":"inactive","last_pulled":null,"last_pushed":null},{"architecture":"arm64","features":"","variant":"v8","digest":"sha256:166086b6e1dcc0f8cc6f39b8d33dad532199a305b7a45c575d5154b5fc4f1b27","os":"linux","os_features":"","os_version":null,"size":112825133,"status":"inactive","last_pulled":null,"last_pushed":null}],"last_updated":"2019-01-01T01:44:49.132702Z","last_updater":1156886,"last_updater_username":"doijanky","name":"1.7.1","repository":1288811,"full_size":122491901,"v2":true,"tag_status":"inactive","tag_last_pulled":null,"tag_last_pushed":"2019-01-01T01:44:49.132702Z"},{"creator":1156886,"id":31409570,"image_id":null,"images":[{"architecture":"amd64","features":"","variant":null,"digest":"sha256:9d159adb5681301aafb21070b51a46789375602eb87496307f826f75d360b38a","os":"linux","os_features":"","os_version":null,"size":30835280,"status":"inactive","last_pulled":null,"last_pushed":null},{"architecture":"arm","features":"","variant":"v6","digest":"sha256:cfc3fbaeb3f38576204d652e868c337eb66a5909405ff999e798b9e8d814ade6","os":"linux","os_features":"","os_version":null,"size":29482082,"status":"inactive","last_pulled":null,"last_pushed":null},{"architecture":"arm64","features":"","variant":"v8","digest":"sha256:c4cecc02e8283b6ae55c9271ae3788b538752c46d64d78bab0b11a653c52ac3c","os":"linux","os_features":"","os_version":null,"size":30106779,"status":"inactive","last_pulled":null,"last_pushed":null}],"last_updated":"2018-12-21T10:48:04.598245Z","last_updater":1156886,"last_updater_username":"doijanky","name":"1.7.1-slim","repository":1288811,"full_size":30835280,"v2":true,"tag_status":"inactive","tag_last_pulled":null,"tag_last_pushed":"2018-12-21T10:48:04.598245Z"},{"creator":1156886,"id":26792720,"image_id":null,"images":[{"architecture":"amd64","features":"","variant":null,"digest":"sha256:a3820e50354ce9aa768cc80c025079c57fe8e4a465381a2e78cfedddb8fce330","os":"linux","os_features":"","os_version":null,"size":31102480,"status":"inactive","last_pulled":null,"last_pushed":null},{"architecture":"arm64","features":"","variant":"v8","digest":"sha256:3a9d4dfa0159b401106f2f1d17cca27815d9bc46e3bf9516e1072f9ee7650a5e","os":"linux","os_features":"","os_version":null,"size":30512014,"status":"inactive","last_pulled":null,"last_pushed":null}],"last_updated":"2018-07-11T10:46:39.610221Z","last_updater":1156886,"last_updater_username":"doijanky","name":"1.7.0-slim","repository":1288811,"full_size":31102480,"v2":true,"tag_status":"inactive","tag_last_pulled":null,"tag_last_pushed":"2018-07-11T10:46:39.610221Z"},{"creator":1156886,"id":26795570,"image_id":null,"images":[{"architecture":"amd64","features":"","variant":null,"digest":"sha256:15d5ef71c84dcc4b8b633edb6c5b9774933ea92bd7164a6de6b74ae4c5f74abd","os":"linux","os_features":"","os_version":null,"size":121196633,"status":"inactive","last_pulled":null,"last_pushed":null},{"architecture":"arm64","features":"","variant":"v8","digest":"sha256:ea41be78196b6e8bbd1029dc4559f974cc27d34471c576a0a5beae48b2edf2ae","os":"linux","os_features":"","os_version":null,"size":111955139,"status":"inactive","last_pulled":null,"last_pushed":null}],"last_updated":"2018-07-11T10:46:21.105314Z","last_updater":1156886,"last_updater_username":"doijanky","name":"1.7.0","repository":1288811,"full_size":121196633,"v2":true,"tag_status":"inactive","tag_last_pulled":null,"tag_last_pushed":"2018-07-11T10:46:21.105314Z"},{"creator":2215,"id":8564871,"image_id":null,"images":[{"architecture":"amd64","features":"","variant":null,"digest":"sha256:9fa07312a97398530366d2d9535aca2f9cea885c25db98aca6ff30c0f634463e","os":"linux","os_features":"","os_version":null,"size":23893406,"status":"inactive","last_pulled":null,"last_pushed":null}],"last_updated":"2018-05-03T18:43:47.631097Z","last_updater":1156886,"last_updater_username":"doijanky","name":"1.6-slim","repository":1288811,"full_size":23893406,"v2":true,"tag_status":"inactive","tag_last_pulled":null,"tag_last_pushed":"2018-05-03T18:43:47.631097Z"},{"creator":1156886,"id":23316737,"image_id":null,"images":[{"architecture":"amd64","features":"","variant":null,"digest":"sha256:9fa07312a97398530366d2d9535aca2f9cea885c25db98aca6ff30c0f634463e","os":"linux","os_features":"","os_version":null,"size":23893406,"status":"inactive","last_pulled":null,"last_pushed":null}],"last_updated":"2018-05-03T18:43:47.326876Z","last_updater":1156886,"last_updater_username":"doijanky","name":"1.6.6-slim","repository":1288811,"full_size":23893406,"v2":true,"tag_status":"inactive","tag_last_pulled":null,"tag_last_pushed":"2018-05-03T18:43:47.326876Z"},{"creator":2215,"id":8564825,"image_id":null,"images":[{"architecture":"amd64","features":"","variant":null,"digest":"sha256:a7fc05a35e1fe2a941041f982b2ef55ebd8dac50bfa594401362f849f69dba4f","os":"linux","os_features":"","os_version":null,"size":105514366,"status":"inactive","last_pulled":null,"last_pushed":null}],"last_updated":"2018-05-03T18:43:37.967362Z","last_updater":1156886,"last_updater_username":"doijanky","name":"1.6","repository":1288811,"full_size":105514366,"v2":true,"tag_status":"inactive","tag_last_pulled":null,"tag_last_pushed":"2018-05-03T18:43:37.967362Z"},{"creator":1156886,"id":23316725,"image_id":null,"images":[{"architecture":"amd64","features":"","variant":null,"digest":"sha256:a7fc05a35e1fe2a941041f982b2ef55ebd8dac50bfa594401362f849f69dba4f","os":"linux","os_features":"","os_version":null,"size":105514366,"status":"inactive","last_pulled":null,"last_pushed":null}],"last_updated":"2018-05-03T18:43:37.654539Z","last_updater":1156886,"last_updater_username":"doijanky","name":"1.6.6","repository":1288811,"full_size":105514366,"v2":true,"tag_status":"inactive","tag_last_pulled":null,"tag_last_pushed":"2018-05-03T18:43:37.654539Z"},{"creator":2215,"id":8949267,"image_id":null,"images":[{"architecture":"amd64","features":"","variant":null,"digest":"sha256:145e5a0868b9ec62982b38d3969119e83723ea2c23a2bbe3109a54cdea3e26b0","os":"linux","os_features":"","os_version":null,"size":23491753,"status":"inactive","last_pulled":null,"last_pushed":null},{"architecture":"arm","features":"","variant":"v6","digest":"sha256:b1cb66f23f3fc9daff6557d551bd9795bc11093463b91db6d693a9c22404e8e8","os":"linux","os_features":"","os_version":null,"size":23334601,"status":"inactive","last_pulled":null,"last_pushed":null}],"last_updated":"2018-02-27T03:43:46.327143Z","last_updater":1156886,"last_updater_username":"doijanky","name":"1.6.5-slim","repository":1288811,"full_size":23491753,"v2":true,"tag_status":"inactive","tag_last_pulled":null,"tag_last_pushed":"2018-02-27T03:43:46.327143Z"},{"creator":2215,"id":8949239,"image_id":null,"images":[{"architecture":"amd64","features":"","variant":null,"digest":"sha256:b687b33cc6d197b8869ecb4958dd44eafa108acf7ea04abfe6590004e41debd6","os":"linux","os_features":"","os_version":null,"size":105113289,"status":"inactive","last_pulled":null,"last_pushed":null},{"architecture":"arm","features":"","variant":"v6","digest":"sha256:edeffd546b4b0d1d331240a02f431966804f4b9b1443783b9b95a664cbdb71ca","os":"linux","os_features":"","os_version":null,"size":94342486,"status":"inactive","last_pulled":null,"last_pushed":null}],"last_updated":"2018-02-27T03:43:29.972851Z","last_updater":1156886,"last_updater_username":"doijanky","name":"1.6.5","repository":1288811,"full_size":105113289,"v2":true,"tag_status":"inactive","tag_last_pulled":null,"tag_last_pushed":"2018-02-27T03:43:29.972851Z"},{"creator":2215,"id":8564856,"image_id":null,"images":[{"architecture":"amd64","features":"","variant":null,"digest":"sha256:fa68553b7eca418451feef39c3ec6795e232bd9c3af0d4af12b2ec8410e4d926","os":"linux","os_features":"","os_version":null,"size":22012929,"status":"inactive","last_pulled":null,"last_pushed":null}],"last_updated":"2017-03-07T18:02:37.579935Z","last_updater":2215,"last_updater_username":"stackbrew","name":"1.6.4-slim","repository":1288811,"full_size":22012929,"v2":true,"tag_status":"inactive","tag_last_pulled":null,"tag_last_pushed":"2017-03-07T18:02:37.579935Z"},{"creator":2215,"id":8564815,"image_id":null,"images":[{"architecture":"amd64","features":"","variant":null,"digest":"sha256:b1307fc4e0b79421bddb3309846cacf4abef96311f913104bf4a8641e25af447","os":"linux","os_features":"","os_version":null,"size":106743282,"status":"inactive","last_pulled":null,"last_pushed":null}],"last_updated":"2017-03-07T18:01:12.380692Z","last_updater":2215,"last_updater_username":"stackbrew","name":"1.6.4","repository":1288811,"full_size":106743282,"v2":true,"tag_status":"inactive","tag_last_pulled":null,"tag_last_pushed":"2017-03-07T18:01:12.380692Z"}]}
